denise/denise.py
denise/fireworks.py
denise-0.3.2.dist-info/entry_points.txt
denise-0.3.2.dist-info/WHEEL
denise-0.3.2.dist-info/METADATA
denise-0.3.2.dist-info/RECORD
