Metadata-Version: 2.1
Name: denise
Version: 0.3.2
Summary: A package containing love
License: MIT
Keywords: love
Author: Matthew Jones
Author-email: you@example.com
Requires-Python: >=3.8,<4.0
Classifier: License :: OSI Approved :: MIT License
Classifier: Programming Language :: Python :: 3
Classifier: Programming Language :: Python :: 3.8
Classifier: Programming Language :: Python :: 3.9
Requires-Dist: asciimatics (>=1.13.0,<2.0.0)
Requires-Dist: click (>=7.1.2,<8.0.0)
Requires-Dist: python-dateutil (>=2.8.1,<3.0.0)
